code_star_cli/__init__.py
code_star_cli/__main__.py
code_star_cli/commands/__init__.py
code_star_cli/commands/ai.py
code_star_cli/commands/chat.py
code_star_cli/commands/completions.py
code_star_cli/commands/document.py
code_star_cli/commands/enhance.py
code_star_cli/commands/review.py
code_star_cli/commands/scan.py
code_star_cli/commands/test.py
code_star_cli/main.py
code_star_cli-0.2.4.dist-info/LICENSE
code_star_cli-0.2.4.dist-info/METADATA
code_star_cli-0.2.4.dist-info/WHEEL
code_star_cli-0.2.4.dist-info/entry_points.txt
code_star_cli-0.2.4.dist-info/RECORD
