Metadata-Version: 2.1
Name: code-star-cli
Version: 0.2.4
Summary: CodeStar is an advanced AI-powered coding assistant designed to enhance developer productivity by providing intelligent code suggestions and natural language interactions. Built on Hugging Face's StarCoder 2 (15B) and StarChat 2 15B.
Home-page: https://github.com/youzarsiph/code-star-cli
License: MIT
Author: Yousef Abu Shanab
Author-email: josephyousef249@gmail.com
Requires-Python: >=3.10,<4.0
Classifier: License :: OSI Approved :: MIT License
Classifier: Programming Language :: Python :: 3
Classifier: Programming Language :: Python :: 3.10
Classifier: Programming Language :: Python :: 3.11
Classifier: Programming Language :: Python :: 3.12
Classifier: Programming Language :: Python :: 3.13
Requires-Dist: huggingface-hub (>=0.25.0,<0.26.0)
Requires-Dist: typer (>=0.12.5,<0.13.0)
Project-URL: Repository, https://github.com/youzarsiph/code-star-cli
